Workbook

Sheet Investor_Profile
A1: Stock Market Portfolio Risk & Return Analyzer
A2: Simulated educational data — not live market prices. For learning/portfolio-showcase purposes only.
A4: Investor Profile | B4: Mr. Arjun Mehta, 34, salaried IT professional
A5: Investment Objective | B5: Long-term wealth creation with moderate risk
A6: Total Investment Corpus | B6: 1000000
A7: Risk Appetite | B7: Moderate
A8: Investment Horizon | B8: 5 years
A9: Expected Annual Return | B9: 0.13
A10: Maximum Acceptable Annualized Volatility | B10: 0.18
A11: Risk-Free Rate (Annual) | B11: 0.07
A12: Benchmark | B12: NIFTY 50 Index
A13: Data Frequency | B13: Monthly (24 observations, Jan 2024 - Jan 2026)

Sheet Raw_Prices
A1: Raw Monthly Closing Prices (₹) — SIMULATED EDUCATIONAL DATA
A3: Date | B3: A01 Reliance Industries | C3: A02 TCS | D3: A03 Persistent Systems | E3: A04 HDFC Bank | F3: A05 Infosys | G3: A06 ITC Ltd | H3: A07 Sun Pharma | I3: A08 Nifty50 Index ETF | J3: A09 Gold ETF | K3: A10 Liquid/Debt Fund | L3: BENCHMARK_NIFTY50
A4: 2024-01-31 | B4: 2450 | C4: 3650 | D4: 4800 | E4: 1550 | F4: 1480 | G4: 430 | H4: 1420 | I4: 245 | J4: 58 | K4: 1000 | L4: 22000
A5: 2024-02-29 | B5: 2546.33 | C5: 3587.15 | D5: 5034.84 | E5: 1564.38 | F5: 1516.11 | G5: 447.05 | H5: 1459.86 | I5: 244.92 | J5: 58.84 | K5: 1002.41 | L5: 21500.58
A6: 2024-03-31 | B6: 2557.52 | C6: 3642.92 | D6: 4326.57 | E6: 1699.08 | F6: 1550.34 | G6: 434.36 | H6: 1545.04 | I6: 239.62 | J6: 56.69 | K6: 1006.97 | L6: 21595.41
A7: 2024-04-30 | B7: 2679.32 | C7: 3469.7 | D7: 4530.64 | E7: 1504.11 | F7: 1564.71 | G7: 462.21 | H7: 1454.28 | I7: 233.06 | J7: 57.43 | K7: 1010.55 | L7: 22225.98
A8: 2024-05-31 | B8: 2935.91 | C8: 3569.57 | D8: 4455.17 | E8: 1579.99 | F8: 1559.71 | G8: 439.99 | H8: 1361.81 | I8: 227.41 | J8: 58.61 | K8: 1016.44 | L8: 23195.7
A9: 2024-06-30 | B9: 2933.33 | C9: 3498.06 | D9: 4263.94 | E9: 1603.97 | F9: 1458.95 | G9: 453.84 | H9: 1420.74 | I9: 228.95 | J9: 57.21 | K9: 1031.44 | L9: 22290.79
A10: 2024-07-31 | B10: 2930.76 | C10: 3482.02 | D10: 4575.42 | E10: 1598.59 | F10: 1440.17 | G10: 497.24 | H10: 1463.68 | I10: 234.52 | J10: 57.92 | K10: 1029.41 | L10: 22193.16
A11: 2024-08-31 | B11: 3220.49 | C11: 3412.08 | D11: 5082.33 | E11: 1623.22 | F11: 1427.47 | G11: 481.52 | H11: 1503.97 | I11: 239.59 | J11: 58.44 | K11: 1037.9 | L11: 21971.28
A12: 2024-09-30 | B12: 3395.07 | C12: 3762.21 | D12: 5599.79 | E12: 1486.21 | F12: 1380.77 | G12: 474.46 | H12: 1553.74 | I12: 250.31 | J12: 56.51 | K12: 1036.91 | L12: 21594.84
A13: 2024-10-31 | B13: 3348.15 | C13: 3797.29 | D13: 5277.64 | E13: 1486.89 | F13: 1381.62 | G13: 480.15 | H13: 1512.66 | I13: 252.95 | J13: 57.61 | K13: 1040.66 | L13: 23314.18
A14: 2024-11-30 | B14: 3488.24 | C14: 3634.44 | D14: 5225.77 | E14: 1528.73 | F14: 1423.08 | G14: 474.32 | H14: 1552.7 | I14: 270.92 | J14: 59.14 | K14: 1050.92 | L14: 23901.68
A15: 2024-12-31 | B15: 3441.19 | C15: 3820.26 | D15: 5475.63 | E15: 1653.99 | F15: 1575.47 | G15: 448.69 | H15: 1599.28 | I15: 270.62 | J15: 61.8 | K15: 1056.97 | L15: 22911.31
... A28: 2026-01-31 | B28: 2601.95 | C28: 3308.49 | D28: 8442.95 | E28: 1687.16 | F28: 1902.65 | G28: 468.2 | H28: 2507.1 | I28: 315.02 | J28: 87.84 | K28: 1130 | L28: 23871.35

Sheet Portfolio_Holdings
A1: Portfolio Holdings & Allocation | N1: Total Investment (₹) | O1: =Investor_Profile!B6 -> 1000000
A3: Asset ID | B3: Asset Name | C3: Asset Type | D3: Sector | E3: Purchase Price (₹) | F3: Current Price (₹) | G3: Target Weight % | H3: Investment Amount (₹) | I3: Quantity | J3: Current Value (₹) | K3: Portfolio Weight %
A4: A01 | B4: Reliance Industries | C4: Large-Cap | D4: Energy/Conglomerate | E4: =Raw_Prices!B4 -> 2450 | F4: =Raw_Prices!B28 -> 2601.95 | G4: 0.12 | H4: =$O$1*G4 -> 120000 | I4: =H4/E4 -> 48.979592 | J4: =I4*F4 -> 127442.45 | K4: =J4/SUM($J$4:$J$13) -> 0.10073913
A5: A02 | B5: TCS | C5: Large-Cap | D5: Technology | E5: =Raw_Prices!C4 -> 3650 | F5: =Raw_Prices!C28 -> 3308.49 | G5: 0.1 | H5: =$O$1*G5 -> 100000 | I5: =H5/E5 -> 27.39726 | J5: =I5*F5 -> 90643.562 | K5: =J5/SUM($J$4:$J$13) -> 0.071650801
A6: A03 | B6: Persistent Systems | C6: Mid-Cap | D6: Technology | E6: =Raw_Prices!D4 -> 4800 | F6: =Raw_Prices!D28 -> 8442.95 | G6: 0.08 | H6: =$O$1*G6 -> 80000 | I6: =H6/E6 -> 16.666667 | J6: =I6*F6 -> 140715.83 | K6: =J6/SUM($J$4:$J$13) -> 0.11123131
A7: A04 | B7: HDFC Bank | C7: Banking/Financial | D7: Financials | E7: =Raw_Prices!E4 -> 1550 | F7: =Raw_Prices!E28 -> 1687.16 | G7: 0.12 | H7: =$O$1*G7 -> 120000 | I7: =H7/E7 -> 77.419355 | J7: =I7*F7 -> 130618.84 | K7: =J7/SUM($J$4:$J$13) -> 0.10324996
A8: A05 | B8: Infosys | C8: Technology | D8: IT Services | E8: =Raw_Prices!F4 -> 1480 | F8: =Raw_Prices!F28 -> 1902.65 | G8: 0.1 | H8: =$O$1*G8 -> 100000 | I8: =H8/E8 -> 67.567568 | J8: =I8*F8 -> 128557.43 | K8: =J8/SUM($J$4:$J$13) -> 0.10162049
A9: A06 | B9: ITC Ltd | C9: Consumer | D9: FMCG | E9: =Raw_Prices!G4 -> 430 | F9: =Raw_Prices!G28 -> 468.2 | G9: 0.08 | H9: =$O$1*G9 -> 80000 | I9: =H9/E9 -> 186.04651 | J9: =I9*F9 -> 87106.977 | K9: =J9/SUM($J$4:$J$13) -> 0.068855245
A10: A07 | B10: Sun Pharma | C10: Pharma/Healthcare | D10: Healthcare | E10: =Raw_Prices!H4 -> 1420 | F10: =Raw_Prices!H28 -> 2507.1 | G10: 0.08 | H10: =$O$1*G10 -> 80000 | I10: =H10/E10 -> 56.338028 | J10: =I10*F10 -> 141245.07 | K10: =J10/SUM($J$4:$J$13) -> 0.11164966
A11: A08 | B11: Nifty50 Index ETF | C11: Index ETF | D11: Diversified Equity | E11: =Raw_Prices!I4 -> 245 | F11: =Raw_Prices!I28 -> 315.02 | G11: 0.12 | H11: =$O$1*G11 -> 120000 | I11: =H11/E11 -> 489.79592 | J11: =I11*F11 -> 154295.51 | K11: =J11/SUM($J$4:$J$13) -> 0.12196561
A12: A09 | B12: Gold ETF | C12: Gold ETF | D12: Commodity | E12: =Raw_Prices!J4 -> 58 | F12: =Raw_Prices!J28 -> 87.84 | G12: 0.1 | H12: =$O$1*G12 -> 100000 | I12: =H12/E12 -> 1724.1379 | J12: =I12*F12 -> 151448.28 | K12: =J12/SUM($J$4:$J$13) -> 0.11971496
A13: A10 | B13: Liquid/Debt Fund | C13: Debt Fund | D13: Fixed Income | E13: =Raw_Prices!K4 -> 1000 | F13: =Raw_Prices!K28 -> 1130 | G13: 0.1 | H13: =$O$1*G13 -> 100000 | I13: =H13/E13 -> 100 | J13: =I13*F13 -> 113000 | K13: =J13/SUM($J$4:$J$13) -> 0.089322842
B14: TOTAL | G14: =SUM(G4:G13) -> 1 | H14: =SUM(H4:H13) -> 1000000 | J14: =SUM(J4:J13) -> 1265073.9 | K14: =SUM(K4:K13) -> 1

Sheet Returns
A1: Monthly Returns (%) by Asset
A3: Date | B3: A01 | C3: A02 | D3: A03 | E3: A04 | F3: A05 | G3: A06 | H3: A07 | I3: A08 | J3: A09 | K3: A10 | L3: Portfolio Return % | M3: Benchmark Return %
A4: =Raw_Prices!A5 -> 2024-02-29 | B4: =(Raw_Prices!B5-Raw_Prices!B4)/Raw_Prices!B4 -> 0.039318367 | C4: =(Raw_Prices!C5-Raw_Prices!C4)/Raw_Prices!C4 -> -0.017219178 | D4: =(Raw_Prices!D5-Raw_Prices!D4)/Raw_Prices!D4 -> 0.048925 | E4: =(Raw_Prices!E5-Raw_Prices!E4)/Raw_Prices!E4 -> 0.0092774194 | F4: =(Raw_Prices!F5-Raw_Prices!F4)/Raw_Prices!F4 -> 0.024398649 | G4: =(Raw_Prices!G5-Raw_Prices!G4)/Raw_Prices!G4 -> 0.039651163 | H4: =(Raw_Prices!H5-Raw_Prices!H4)/Raw_Prices!H4 -> 0.028070423 | I4: =(Raw_Prices!I5-Raw_Prices!I4)/Raw_Prices!I4 -> -0.00032653061 | ... K4: =(Raw_Prices!K5-Raw_Prices!K4)/Raw_Prices!K4 -> 0.00241 | L4: =B4*Portfolio_Holdings!$K$4+C4*Portfolio_Holdings!$K$5+D4*Portfolio_Holdings!$K$6+E4*Portfolio_Holdings!$K$7+F4*Portfolio_Holdings!$K$8+G4*Portfolio_Holdings!$K$9+H4*Portfolio_Holdings!$K$10+I4*Portfolio_Holdings!$K$11+J4*Portfolio_Holdings!$K$12+K4*Portfolio_Holdings!$K$13 -> 0.019379907 | M4: =(Raw_Prices!L5-Raw_Prices!L4)/Raw_Prices!L4 -> -0.022700909
A5: =Raw_Prices!A6 -> 2024-03-31 | B5: =(Raw_Prices!B6-Raw_Prices!B5)/Raw_Prices!B5 -> 0.00439456 | C5: =(Raw_Prices!C6-Raw_Prices!C5)/Raw_Prices!C5 -> 0.015547161 | D5: =(Raw_Prices!D6-Raw_Prices!D5)/Raw_Prices!D5 -> -0.14067379 | E5: =(Raw_Prices!E6-Raw_Prices!E5)/Raw_Prices!E5 -> 0.086104399 | F5: =(Raw_Prices!F6-Raw_Prices!F5)/Raw_Prices!F5 -> 0.022577517 | G5: =(Raw_Prices!G6-Raw_Prices!G5)/Raw_Prices!G5 -> -0.028386087 | H5: =(Raw_Prices!H6-Raw_Prices!H5)/Raw_Prices!H5 -> 0.058348061 | I5: =(Raw_Prices!I6-Raw_Prices!I5)/Raw_Prices!I5 -> -0.021639719 | ... K5: =(Raw_Prices!K6-Raw_Prices!K5)/Raw_Prices!K5 -> 0.0045490368 | L5: =B5*Portfolio_Holdings!$K$4+C5*Portfolio_Holdings!$K$5+D5*Portfolio_Holdings!$K$6+E5*Portfolio_Holdings!$K$7+F5*Portfolio_Holdings!$K$8+G5*Portfolio_Holdings!$K$9+H5*Portfolio_Holdings!$K$10+I5*Portfolio_Holdings!$K$11+J5*Portfolio_Holdings!$K$12+K5*Portfolio_Holdings!$K$13 -> -0.0049533599 | M5: =(Raw_Prices!L6-Raw_Prices!L5)/Raw_Prices!L5 -> 0.0044105787
A6: =Raw_Prices!A7 -> 2024-04-30 | B6: =(Raw_Prices!B7-Raw_Prices!B6)/Raw_Prices!B6 -> 0.047624261 | C6: =(Raw_Prices!C7-Raw_Prices!C6)/Raw_Prices!C6 -> -0.047549768 | D6: =(Raw_Prices!D7-Raw_Prices!D6)/Raw_Prices!D6 -> 0.047166693 | E6: =(Raw_Prices!E7-Raw_Prices!E6)/Raw_Prices!E6 -> -0.11475034 | F6: =(Raw_Prices!F7-Raw_Prices!F6)/Raw_Prices!F6 -> 0.0092689346 | G6: =(Raw_Prices!G7-Raw_Prices!G6)/Raw_Prices!G6 -> 0.064117322 | H6: =(Raw_Prices!H7-Raw_Prices!H6)/Raw_Prices!H6 -> -0.058742816 | I6: =(Raw_Prices!I7-Raw_Prices!I6)/Raw_Prices!I6 -> -0.02737668 | ... K6: =(Raw_Prices!K7-Raw_Prices!K6)/Raw_Prices!K6 -> 0.0035552201 | L6: =B6*Portfolio_Holdings!$K$4+C6*Portfolio_Holdings!$K$5+D6*Portfolio_Holdings!$K$6+E6*Portfolio_Holdings!$K$7+F6*Portfolio_Holdings!$K$8+G6*Portfolio_Holdings!$K$9+H6*Portfolio_Holdings!$K$10+I6*Portfolio_Holdings!$K$11+J6*Portfolio_Holdings!$K$12+K6*Portfolio_Holdings!$K$13 -> -0.0078715526 | M6: =(Raw_Prices!L7-Raw_Prices!L6)/Raw_Prices!L6 -> 0.02919926
A7: =Raw_Prices!A8 -> 2024-05-31 | B7: =(Raw_Prices!B8-Raw_Prices!B7)/Raw_Prices!B7 -> 0.095766836 | C7: =(Raw_Prices!C8-Raw_Prices!C7)/Raw_Prices!C7 -> 0.028783468 | D7: =(Raw_Prices!D8-Raw_Prices!D7)/Raw_Prices!D7 -> -0.016657691 | E7: =(Raw_Prices!E8-Raw_Prices!E7)/Raw_Prices!E7 -> 0.050448438 | F7: =(Raw_Prices!F8-Raw_Prices!F7)/Raw_Prices!F7 -> -0.0031954803 | G7: =(Raw_Prices!G8-Raw_Prices!G7)/Raw_Prices!G7 -> -0.048073387 | H7: =(Raw_Prices!H8-Raw_Prices!H7)/Raw_Prices!H7 -> -0.063584729 | I7: =(Raw_Prices!I8-Raw_Prices!I7)/Raw_Prices!I7 -> -0.024242684 | ... K7: =(Raw_Prices!K8-Raw_Prices!K7)/Raw_Prices!K7 -> 0.0058285092 | L7: =B7*Portfolio_Holdings!$K$4+C7*Portfolio_Holdings!$K$5+D7*Portfolio_Holdings!$K$6+E7*Portfolio_Holdings!$K$7+F7*Portfolio_Holdings!$K$8+G7*Portfolio_Holdings!$K$9+H7*Portfolio_Holdings!$K$10+I7*Portfolio_Holdings!$K$11+J7*Portfolio_Holdings!$K$12+K7*Portfolio_Holdings!$K$13 -> 0.0043553237 | M7: =(Raw_Prices!L8-Raw_Prices!L7)/Raw_Prices!L7 -> 0.043630022
A8: =Raw_Prices!A9 -> 2024-06-30 | B8: =(Raw_Prices!B9-Raw_Prices!B8)/Raw_Prices!B8 -> -0.00087877353 | C8: =(Raw_Prices!C9-Raw_Prices!C8)/Raw_Prices!C8 -> -0.020033225 | D8: =(Raw_Prices!D9-Raw_Prices!D8)/Raw_Prices!D8 -> -0.042923166 | E8: =(Raw_Prices!E9-Raw_Prices!E8)/Raw_Prices!E8 -> 0.015177311 | F8: =(Raw_Prices!F9-Raw_Prices!F8)/Raw_Prices!F8 -> -0.064601753 | G8: =(Raw_Prices!G9-Raw_Prices!G8)/Raw_Prices!G8 -> 0.031477988 | H8: =(Raw_Prices!H9-Raw_Prices!H8)/Raw_Prices!H8 -> 0.043273291 | I8: =(Raw_Prices!I9-Raw_Prices!I8)/Raw_Prices!I8 -> 0.0067719098 | ... K8: =(Raw_Prices!K9-Raw_Prices!K8)/Raw_Prices!K8 -> 0.014757389 | L8: =B8*Portfolio_Holdings!$K$4+C8*Portfolio_Holdings!$K$5+D8*Portfolio_Holdings!$K$6+E8*Portfolio_Holdings!$K$7+F8*Portfolio_Holdings!$K$8+G8*Portfolio_Holdings!$K$9+H8*Portfolio_Holdings!$K$10+I8*Portfolio_Holdings!$K$11+J8*Portfolio_Holdings!$K$12+K8*Portfolio_Holdings!$K$13 -> -0.0050127402 | M8: =(Raw_Prices!L9-Raw_Prices!L8)/Raw_Prices!L8 -> -0.039011972
A9: =Raw_Prices!A10 -> 2024-07-31 | B9: =(Raw_Prices!B10-Raw_Prices!B9)/Raw_Prices!B9 -> -0.00087613736 | C9: =(Raw_Prices!C10-Raw_Prices!C9)/Raw_Prices!C9 -> -0.0045853988 | D9: =(Raw_Prices!D10-Raw_Prices!D9)/Raw_Prices!D9 -> 0.073049808 | E9: =(Raw_Prices!E10-Raw_Prices!E9)/Raw_Prices!E9 -> -0.0033541774 | F9: =(Raw_Prices!F10-Raw_Prices!F9)/Raw_Prices!F9 -> -0.012872271 | G9: =(Raw_Prices!G10-Raw_Prices!G9)/Raw_Prices!G9 -> 0.095628415 | H9: =(Raw_Prices!H10-Raw_Prices!H9)/Raw_Prices!H9 -> 0.030223686 | I9: =(Raw_Prices!I10-Raw_Prices!I9)/Raw_Prices!I9 -> 0.024328456 | ... K9: =(Raw_Prices!K10-Raw_Prices!K9)/Raw_Prices!K9 -> -0.0019681222 | L9: =B9*Portfolio_Holdings!$K$4+C9*Portfolio_Holdings!$K$5+D9*Portfolio_Holdings!$K$6+E9*Portfolio_Holdings!$K$7+F9*Portfolio_Holdings!$K$8+G9*Portfolio_Holdings!$K$9+H9*Portfolio_Holdings!$K$10+I9*Portfolio_Holdings!$K$11+J9*Portfolio_Holdings!$K$12+K9*Portfolio_Holdings!$K$13 -> 0.020290343 | M9: =(Raw_Prices!L10-Raw_Prices!L9)/Raw_Prices!L9 -> -0.0043798358
A10: =Raw_Prices!A11 -> 2024-08-31 | B10: =(Raw_Prices!B11-Raw_Prices!B10)/Raw_Prices!B10 -> 0.098858317 | C10: =(Raw_Prices!C11-Raw_Prices!C10)/Raw_Prices!C10 -> -0.020086042 | D10: =(Raw_Prices!D11-Raw_Prices!D10)/Raw_Prices!D10 -> 0.11078983 | E10: =(Raw_Prices!E11-Raw_Prices!E10)/Raw_Prices!E10 -> 0.015407328 | F10: =(Raw_Prices!F11-Raw_Prices!F10)/Raw_Prices!F10 -> -0.0088184034 | G10: =(Raw_Prices!G11-Raw_Prices!G10)/Raw_Prices!G10 -> -0.031614512 | H10: =(Raw_Prices!H11-Raw_Prices!H10)/Raw_Prices!H10 -> 0.027526509 | I10: =(Raw_Prices!I11-Raw_Prices!I10)/Raw_Prices!I10 -> 0.021618625 | ... K10: =(Raw_Prices!K11-Raw_Prices!K10)/Raw_Prices!K10 -> 0.0082474427 | L10: =B10*Portfolio_Holdings!$K$4+C10*Portfolio_Holdings!$K$5+D10*Portfolio_Holdings!$K$6+E10*Portfolio_Holdings!$K$7+F10*Portfolio_Holdings!$K$8+G10*Portfolio_Holdings!$K$9+H10*Portfolio_Holdings!$K$10+I10*Portfolio_Holdings!$K$11+J10*Portfolio_Holdings!$K$12+K10*Portfolio_Holdings!$K$13 -> 0.026882396 | M10: =(Raw_Prices!L11-Raw_Prices!L10)/Raw_Prices!L10 -> -0.009997675
A11: =Raw_Prices!A12 -> 2024-09-30 | B11: =(Raw_Prices!B12-Raw_Prices!B11)/Raw_Prices!B11 -> 0.054209142 | C11: =(Raw_Prices!C12-Raw_Prices!C11)/Raw_Prices!C11 -> 0.10261483 | D11: =(Raw_Prices!D12-Raw_Prices!D11)/Raw_Prices!D11 -> 0.10181551 | E11: =(Raw_Prices!E12-Raw_Prices!E11)/Raw_Prices!E11 -> -0.084406304 | F11: =(Raw_Prices!F12-Raw_Prices!F11)/Raw_Prices!F11 -> -0.032715223 | G11: =(Raw_Prices!G12-Raw_Prices!G11)/Raw_Prices!G11 -> -0.014661904 | H11: =(Raw_Prices!H12-Raw_Prices!H11)/Raw_Prices!H11 -> 0.033092415 | I11: =(Raw_Prices!I12-Raw_Prices!I11)/Raw_Prices!I11 -> 0.044743103 | ... K11: =(Raw_Prices!K12-Raw_Prices!K11)/Raw_Prices!K11 -> -0.00095384912 | L11: =B11*Portfolio_Holdings!$K$4+C11*Portfolio_Holdings!$K$5+D11*Portfolio_Holdings!$K$6+E11*Portfolio_Holdings!$K$7+F11*Portfolio_Holdings!$K$8+G11*Portfolio_Holdings!$K$9+H11*Portfolio_Holdings!$K$10+I11*Portfolio_Holdings!$K$11+J11*Portfolio_Holdings!$K$12+K11*Portfolio_Holdings!$K$13 -> 0.016202505 | M11: =(Raw_Prices!L12-Raw_Prices!L11)/Raw_Prices!L11 -> -0.017133276
A12: =Raw_Prices!A13 -> 2024-10-31 | B12: =(Raw_Prices!B13-Raw_Prices!B12)/Raw_Prices!B12 -> -0.013820039 | C12: =(Raw_Prices!C13-Raw_Prices!C12)/Raw_Prices!C12 -> 0.0093243067 | D12: =(Raw_Prices!D13-Raw_Prices!D12)/Raw_Prices!D12 -> -0.057528943 | E12: =(Raw_Prices!E13-Raw_Prices!E12)/Raw_Prices!E12 -> 0.00045753965 | F12: =(Raw_Prices!F13-Raw_Prices!F12)/Raw_Prices!F12 -> 0.00061559854 | G12: =(Raw_Prices!G13-Raw_Prices!G12)/Raw_Prices!G12 -> 0.011992581 | H12: =(Raw_Prices!H13-Raw_Prices!H12)/Raw_Prices!H12 -> -0.02643943 | I12: =(Raw_Prices!I13-Raw_Prices!I12)/Raw_Prices!I12 -> 0.010546922 | ... K12: =(Raw_Prices!K13-Raw_Prices!K12)/Raw_Prices!K12 -> 0.0036165145 | L12: =B12*Portfolio_Holdings!$K$4+C12*Portfolio_Holdings!$K$5+D12*Portfolio_Holdings!$K$6+E12*Portfolio_Holdings!$K$7+F12*Portfolio_Holdings!$K$8+G12*Portfolio_Holdings!$K$9+H12*Portfolio_Holdings!$K$10+I12*Portfolio_Holdings!$K$11+J12*Portfolio_Holdings!$K$12+K12*Portfolio_Holdings!$K$13 -> -0.0051998268 | M12: =(Raw_Prices!L13-Raw_Prices!L12)/Raw_Prices!L12 -> 0.079618094
A13: =Raw_Prices!A14 -> 2024-11-30 | B13: =(Raw_Prices!B14-Raw_Prices!B13)/Raw_Prices!B13 -> 0.041841017 | C13: =(Raw_Prices!C14-Raw_Prices!C13)/Raw_Prices!C13 -> -0.042885848 | D13: =(Raw_Prices!D14-Raw_Prices!D13)/Raw_Prices!D13 -> -0.0098282566 | E13: =(Raw_Prices!E14-Raw_Prices!E13)/Raw_Prices!E13 -> 0.028139271 | F13: =(Raw_Prices!F14-Raw_Prices!F13)/Raw_Prices!F13 -> 0.030008251 | G13: =(Raw_Prices!G14-Raw_Prices!G13)/Raw_Prices!G13 -> -0.012142039 | H13: =(Raw_Prices!H14-Raw_Prices!H13)/Raw_Prices!H13 -> 0.026469927 | I13: =(Raw_Prices!I14-Raw_Prices!I13)/Raw_Prices!I13 -> 0.071041708 | ... K13: =(Raw_Prices!K14-Raw_Prices!K13)/Raw_Prices!K13 -> 0.0098591279 | L13: =B13*Portfolio_Holdings!$K$4+C13*Portfolio_Holdings!$K$5+D13*Portfolio_Holdings!$K$6+E13*Portfolio_Holdings!$K$7+F13*Portfolio_Holdings!$K$8+G13*Portfolio_Holdings!$K$9+H13*Portfolio_Holdings!$K$10+I13*Portfolio_Holdings!$K$11+J13*Portfolio_Holdings!$K$12+K13*Portfolio_Holdings!$K$13 -> 0.020847826 | M13: =(Raw_Prices!L14-Raw_Prices!L13)/Raw_Prices!L13 -> 0.025199256
A14: =Raw_Prices!A15 -> 2024-12-31 | B14: =(Raw_Prices!B15-Raw_Prices!B14)/Raw_Prices!B14 -> -0.013488177 | C14: =(Raw_Prices!C15-Raw_Prices!C14)/Raw_Prices!C14 -> 0.051127546 | D14: =(Raw_Prices!D15-Raw_Prices!D14)/Raw_Prices!D14 -> 0.04781305 | E14: =(Raw_Prices!E15-Raw_Prices!E14)/Raw_Prices!E14 -> 0.081937294 | F14: =(Raw_Prices!F15-Raw_Prices!F14)/Raw_Prices!F14 -> 0.10708463 | G14: =(Raw_Prices!G15-Raw_Prices!G14)/Raw_Prices!G14 -> -0.05403525 | H14: =(Raw_Prices!H15-Raw_Prices!H14)/Raw_Prices!H14 -> 0.029999356 | I14: =(Raw_Prices!I15-Raw_Prices!I14)/Raw_Prices!I14 -> -0.001107338 | ... K14: =(Raw_Prices!K15-Raw_Prices!K14)/Raw_Prices!K14 -> 0.0057568607 | L14: =B14*Portfolio_Holdings!$K$4+C14*Portfolio_Holdings!$K$5+D14*Portfolio_Holdings!$K$6+E14*Portfolio_Holdings!$K$7+F14*Portfolio_Holdings!$K$8+G14*Portfolio_Holdings!$K$9+H14*Portfolio_Holdings!$K$10+I14*Portfolio_Holdings!$K$11+J14*Portfolio_Holdings!$K$12+K14*Portfolio_Holdings!$K$13 -> 0.032357377 | M14: =(Raw_Prices!L15-Raw_Prices!L14)/Raw_Prices!L14 -> -0.041435163
A15: =Raw_Prices!A16 -> 2025-01-31 | B15: =(Raw_Prices!B16-Raw_Prices!B15)/Raw_Prices!B15 -> -0.013614476 | C15: =(Raw_Prices!C16-Raw_Prices!C15)/Raw_Prices!C15 -> -0.051041029 | D15: =(Raw_Prices!D16-Raw_Prices!D15)/Raw_Prices!D15 -> 0.1057997 | E15: =(Raw_Prices!E16-Raw_Prices!E15)/Raw_Prices!E15 -> -0.013875537 | F15: =(Raw_Prices!F16-Raw_Prices!F15)/Raw_Prices!F15 -> 0.018077145 | G15: =(Raw_Prices!G16-Raw_Prices!G15)/Raw_Prices!G15 -> 0.010742383 | H15: =(Raw_Prices!H16-Raw_Prices!H15)/Raw_Prices!H15 -> -0.028431544 | I15: =(Raw_Prices!I16-Raw_Prices!I15)/Raw_Prices!I15 -> 0.12423324 | ... K15: =(Raw_Prices!K16-Raw_Prices!K15)/Raw_Prices!K15 -> 0.0011920868 | L15: =B15*Portfolio_Holdings!$K$4+C15*Portfolio_Holdings!$K$5+D15*Portfolio_Holdings!$K$6+E15*Portfolio_Holdings!$K$7+F15*Portfolio_Holdings!$K$8+G15*Portfolio_Holdings!$K$9+H15*Portfolio_Holdings!$K$10+I15*Portfolio_Holdings!$K$11+J15*Portfolio_Holdings!$K$12+K15*Portfolio_Holdings!$K$13 -> 0.025217555 | M15: =(Raw_Prices!L16-Raw_Prices!L15)/Raw_Prices!L15 -> 0.04571454
... A27: =Raw_Prices!A28 -> 2026-01-31 | B27: =(Raw_Prices!B28-Raw_Prices!B27)/Raw_Prices!B27 -> -0.06636071 | C27: =(Raw_Prices!C28-Raw_Prices!C27)/Raw_Prices!C27 -> 0.062855986 | D27: =(Raw_Prices!D28-Raw_Prices!D27)/Raw_Prices!D27 -> 0.15642275 | E27: =(Raw_Prices!E28-Raw_Prices!E27)/Raw_Prices!E27 -> -0.059249925 | F27: =(Raw_Prices!F28-Raw_Prices!F27)/Raw_Prices!F27 -> 0.048101447 | G27: =(Raw_Prices!G28-Raw_Prices!G27)/Raw_Prices!G27 -> 0.015375941 | H27: =(Raw_Prices!H28-Raw_Prices!H27)/Raw_Prices!H27 -> 0.12301621 | I27: =(Raw_Prices!I28-Raw_Prices!I27)/Raw_Prices!I27 -> 0.045952586 | ... K27: =(Raw_Prices!K28-Raw_Prices!K27)/Raw_Prices!K27 -> 0.0089105552 | L27: =B27*Portfolio_Holdings!$K$4+C27*Portfolio_Holdings!$K$5+D27*Portfolio_Holdings!$K$6+E27*Portfolio_Holdings!$K$7+F27*Portfolio_Holdings!$K$8+G27*Portfolio_Holdings!$K$9+H27*Portfolio_Holdings!$K$10+I27*Portfolio_Holdings!$K$11+J27*Portfolio_Holdings!$K$12+K27*Portfolio_Holdings!$K$13 -> 0.039196637 | M27: =(Raw_Prices!L28-Raw_Prices!L27)/Raw_Prices!L27 -> -0.031975445
A30: Annualized Return % (avg monthly x 12, simple) | B30: =AVERAGE(B4:B27)*12 -> 0.046560975 | C30: =AVERAGE(C4:C27)*12 -> -0.037776103 | D30: =AVERAGE(D4:D27)*12 -> 0.32057218 | E30: =AVERAGE(E4:E27)*12 -> 0.055625372 | F30: =AVERAGE(F4:F27)*12 -> 0.13952404 | G30: =AVERAGE(G4:G27)*12 -> 0.052961163 | H30: =AVERAGE(H4:H27)*12 -> 0.30335918 | I30: =AVERAGE(I4:I27)*12 -> 0.13480038 | ... M30: =AVERAGE(M4:M27)*12 -> 0.054088614
A33: Portfolio Max Drawdown Calculation (Wealth Index, base=100)
A34: Date | B34: Portfolio Return % | C34: Wealth Index | D34: Running Peak | E34: Drawdown %
A35: =A4 -> 2024-02-29 | B35: =L4 -> 0.019379907 | C35: =100*(1+B35) -> 101.93799 | D35: =MAX($C$35:C35) -> 101.93799 | E35: =C35/D35-1 -> 0
A36: =A5 -> 2024-03-31 | B36: =L5 -> -0.0049533599 | C36: =C35*(1+B36) -> 101.43306 | D36: =MAX($C$35:C36) -> 101.93799 | E36: =C36/D36-1 -> -0.0049533599
A37: =A6 -> 2024-04-30 | B37: =L6 -> -0.0078715526 | C37: =C36*(1+B37) -> 100.63462 | D37: =MAX($C$35:C37) -> 101.93799 | E37: =C37/D37-1 -> -0.012785922
A38: =A7 -> 2024-05-31 | B38: =L7 -> 0.0043553237 | C38: =C37*(1+B38) -> 101.07292 | D38: =MAX($C$35:C38) -> 101.93799 | E38: =C38/D38-1 -> -0.008486285
A39: =A8 -> 2024-06-30 | B39: =L8 -> -0.0050127402 | C39: =C38*(1+B39) -> 100.56626 | D39: =MAX($C$35:C39) -> 101.93799 | E39: =C39/D39-1 -> -0.013456486
A40: =A9 -> 2024-07-31 | B40: =L9 -> 0.020290343 | C40: =C39*(1+B40) -> 102.60679 | D40: =MAX($C$35:C40) -> 102.60679 | E40: =C40/D40-1 -> 0
A41: =A10 -> 2024-08-31 | B41: =L10 -> 0.026882396 | C41: =C40*(1+B41) -> 105.3651 | D41: =MAX($C$35:C41) -> 105.3651 | E41: =C41/D41-1 -> 0
A42: =A11 -> 2024-09-30 | B42: =L11 -> 0.016202505 | C42: =C41*(1+B42) -> 107.07228 | D42: =MAX($C$35:C42) -> 107.07228 | E42: =C42/D42-1 -> 0
A43: =A12 -> 2024-10-31 | B43: =L12 -> -0.0051998268 | C43: =C42*(1+B43) -> 106.51553 | D43: =MAX($C$35:C43) -> 107.07228 | E43: =C43/D43-1 -> -0.0051998268
A44: =A13 -> 2024-11-30 | B44: =L13 -> 0.020847826 | C44: =C43*(1+B44) -> 108.73614 | D44: =MAX($C$35:C44) -> 108.73614 | E44: =C44/D44-1 -> 0
A45: =A14 -> 2024-12-31 | B45: =L14 -> 0.032357377 | C45: =C44*(1+B45) -> 112.25456 | D45: =MAX($C$35:C45) -> 112.25456 | E45: =C45/D45-1 -> 0
A46: =A15 -> 2025-01-31 | B46: =L15 -> 0.025217555 | C46: =C45*(1+B46) -> 115.08534 | D46: =MAX($C$35:C46) -> 115.08534 | E46: =C46/D46-1 -> 0
A47: =A16 -> 2025-02-28 | B47: =L16 -> 0.011507406 | C47: =C46*(1+B47) -> 116.40968 | D47: =MAX($C$35:C47) -> 116.40968 | E47: =C47/D47-1 -> 0
... A58: =A27 -> 2026-01-31 | B58: =L27 -> 0.039196637 | C58: =C57*(1+B58) -> 132.27588 | D58: =MAX($C$35:C58) -> 132.27588 | E58: =C58/D58-1 -> 0

Sheet Risk_Analysis
A1: Risk & Risk-Adjusted Performance Analysis
A2: Risk-free rate and formulas below; volatility annualized using sqrt(12) on monthly std dev.
A4: Annual Risk-Free Rate | B4: =Investor_Profile!B11 -> 0.07
A6: Asset ID | B6: Asset Name | C6: Monthly Volatility % | D6: Annualized Volatility % | E6: Beta (vs Benchmark) | F6: Annualized Return % | G6: Sharpe Ratio | H6: Treynor Ratio | I6: Worst Single-Month Return % | J6: 1-Month 95% VaR (₹) | K6: Risk Category
A7: A01 | B7: =Portfolio_Holdings!B4 -> Reliance Industries | C7: =STDEVP(Returns!B4:B27) -> 0.052429144 | D7: =C7*SQRT(12) -> 0.18161988 | E7: =SLOPE(Returns!B4:B27,Returns!M4:M27) -> -0.09043801 | F7: =Returns!B30 -> 0.046560975 | G7: =(F7-$B$4)/D7 -> -0.12905539 | H7: =(F7-$B$4)/E7 -> 0.25917228 | I7: =MIN(Returns!B4:B27) -> -0.093229203 | J7: =1.645*C7*Portfolio_Holdings!J4 -> 10991.394 | K7: =IF(D7<0.15,"Conservative",IF(D7<0.25,"Moderate",IF(D7<0.35,"Aggressive","Very Aggressive"))) -> Moderate
A8: A02 | B8: =Portfolio_Holdings!B5 -> TCS | C8: =STDEVP(Returns!C4:C27) -> 0.043348605 | D8: =C8*SQRT(12) -> 0.15016397 | E8: =SLOPE(Returns!C4:C27,Returns!M4:M27) -> -0.021640596 | F8: =Returns!C30 -> -0.037776103 | G8: =(F8-$B$4)/D8 -> -0.71772278 | H8: =(F8-$B$4)/E8 -> 4.9802742 | I8: =MIN(Returns!C4:C27) -> -0.087982311 | J8: =1.645*C8*Portfolio_Holdings!J5 -> 6463.6523 | K8: =IF(D8<0.15,"Conservative",IF(D8<0.25,"Moderate",IF(D8<0.35,"Aggressive","Very Aggressive"))) -> Moderate
A9: A03 | B9: =Portfolio_Holdings!B6 -> Persistent Systems | C9: =STDEVP(Returns!D4:D27) -> 0.076527694 | D9: =C9*SQRT(12) -> 0.26509971 | E9: =SLOPE(Returns!D4:D27,Returns!M4:M27) -> -0.19097428 | F9: =Returns!D30 -> 0.32057218 | G9: =(F9-$B$4)/D9 -> 0.94519977 | H9: =(F9-$B$4)/E9 -> -1.312073 | I9: =MIN(Returns!D4:D27) -> -0.14067379 | J9: =1.645*C9*Portfolio_Holdings!J6 -> 17714.443 | K9: =IF(D9<0.15,"Conservative",IF(D9<0.25,"Moderate",IF(D9<0.35,"Aggressive","Very Aggressive"))) -> Aggressive
A10: A04 | B10: =Portfolio_Holdings!B7 -> HDFC Bank | C10: =STDEVP(Returns!E4:E27) -> 0.046465873 | D10: =C10*SQRT(12) -> 0.1609625 | E10: =SLOPE(Returns!E4:E27,Returns!M4:M27) -> -0.11143728 | F10: =Returns!E30 -> 0.055625372 | G10: =(F10-$B$4)/D10 -> -0.089304204 | H10: =(F10-$B$4)/E10 -> 0.12899299 | I10: =MIN(Returns!E4:E27) -> -0.11475034 | J10: =1.645*C10*Portfolio_Holdings!J7 -> 9984.0287 | K10: =IF(D10<0.15,"Conservative",IF(D10<0.25,"Moderate",IF(D10<0.35,"Aggressive","Very Aggressive"))) -> Moderate
A11: A05 | B11: =Portfolio_Holdings!B8 -> Infosys | C11: =STDEVP(Returns!F4:F27) -> 0.047541055 | D11: =C11*SQRT(12) -> 0.16468705 | E11: =SLOPE(Returns!F4:F27,Returns!M4:M27) -> -0.10477367 | F11: =Returns!F30 -> 0.13952404 | G11: =(F11-$B$4)/D11 -> 0.42215851 | H11: =(F11-$B$4)/E11 -> -0.66356402 | I11: =MIN(Returns!F4:F27) -> -0.090773412 | J11: =1.645*C11*Portfolio_Holdings!J8 -> 10053.839 | K11: =IF(D11<0.15,"Conservative",IF(D11<0.25,"Moderate",IF(D11<0.35,"Aggressive","Very Aggressive"))) -> Moderate
A12: A06 | B12: =Portfolio_Holdings!B9 -> ITC Ltd | C12: =STDEVP(Returns!G4:G27) -> 0.041781709 | D12: =C12*SQRT(12) -> 0.14473609 | E12: =SLOPE(Returns!G4:G27,Returns!M4:M27) -> 0.072846547 | F12: =Returns!G30 -> 0.052961163 | G12: =(F12-$B$4)/D12 -> -0.11772349 | H12: =(F12-$B$4)/E12 -> -0.23390041 | I12: =MIN(Returns!G4:G27) -> -0.05630142 | J12: =1.645*C12*Portfolio_Holdings!J9 -> 5986.9419 | K12: =IF(D12<0.15,"Conservative",IF(D12<0.25,"Moderate",IF(D12<0.35,"Aggressive","Very Aggressive"))) -> Conservative
A13: A07 | B13: =Portfolio_Holdings!B10 -> Sun Pharma | C13: =STDEVP(Returns!H4:H27) -> 0.051667996 | D13: =C13*SQRT(12) -> 0.17898319 | E13: =SLOPE(Returns!H4:H27,Returns!M4:M27) -> -0.27468217 | F13: =Returns!H30 -> 0.30335918 | G13: =(F13-$B$4)/D13 -> 1.3038051 | H13: =(F13-$B$4)/E13 -> -0.84956072 | I13: =MIN(Returns!H4:H27) -> -0.063584729 | J13: =1.645*C13*Portfolio_Holdings!J10 -> 12004.963 | K13: =IF(D13<0.15,"Conservative",IF(D13<0.25,"Moderate",IF(D13<0.35,"Aggressive","Very Aggressive"))) -> Moderate
A14: A08 | B14: =Portfolio_Holdings!B11 -> Nifty50 Index ETF | C14: =STDEVP(Returns!I4:I27) -> 0.038116473 | D14: =C14*SQRT(12) -> 0.13203934 | E14: =SLOPE(Returns!I4:I27,Returns!M4:M27) -> 0.14772466 | F14: =Returns!I30 -> 0.13480038 | G14: =(F14-$B$4)/D14 -> 0.49076574 | H14: =(F14-$B$4)/E14 -> 0.43865648 | I14: =MIN(Returns!I4:I27) -> -0.053634835 | J14: =1.645*C14*Portfolio_Holdings!J11 -> 9674.5751 | K14: =IF(D14<0.15,"Conservative",IF(D14<0.25,"Moderate",IF(D14<0.35,"Aggressive","Very Aggressive"))) -> Conservative
A15: A09 | B15: =Portfolio_Holdings!B12 -> Gold ETF | C15: =STDEVP(Returns!J4:J27) -> 0.036596474 | D15: =C15*SQRT(12) -> 0.12677391 | E15: =SLOPE(Returns!J4:J27,Returns!M4:M27) -> -0.08350613 | F15: =Returns!J30 -> 0.21705407 | G15: =(F15-$B$4)/D15 -> 1.1599711 | H15: =(F15-$B$4)/E15 -> -1.7609973 | I15: =MIN(Returns!J4:J27) -> -0.041233917 | J15: =1.645*C15*Portfolio_Holdings!J12 -> 9117.368 | K15: =IF(D15<0.15,"Conservative",IF(D15<0.25,"Moderate",IF(D15<0.35,"Aggressive","Very Aggressive"))) -> Conservative
A16: A10 | B16: =Portfolio_Holdings!B13 -> Liquid/Debt Fund | C16: =STDEVP(Returns!K4:K27) -> 0.0042767937 | D16: =C16*SQRT(12) -> 0.014815248 | E16: =SLOPE(Returns!K4:K27,Returns!M4:M27) -> 0.0079560317 | F16: =Returns!K30 -> 0.061373752 | G16: =(F16-$B$4)/D16 -> -0.58225468 | H16: =(F16-$B$4)/E16 -> -1.08424 | I16: =MIN(Returns!K4:K27) -> -0.0025970758 | J16: =1.645*C16*Portfolio_Holdings!J13 -> 794.9918 | K16: =IF(D16<0.15,"Conservative",IF(D16<0.25,"Moderate",IF(D16<0.35,"Aggressive","Very Aggressive"))) -> Conservative
A17: PORTFOLIO | C17: =STDEVP(Returns!L4:L27) -> 0.019761139 | D17: =C17*SQRT(12) -> 0.068454595 | E17: =SLOPE(Returns!L4:L27,Returns!M4:M27) -> -0.070977831 | F17: =Returns!L30 -> 0.14298762 | G17: =(F17-$B$4)/D17 -> 1.0662194 | H17: =(F17-$B$4)/E17 -> -1.0283157 | I17: =MIN(Returns!E35:E58) -> -0.049302737 | J17: =1.645*C17*Portfolio_Holdings!J14 -> 41123.853
A19: Note: for the PORTFOLIO row, the value in 'Worst Single-Month Return %' column is the true peak-to-trough Maximum Drawdown (see Returns sheet wealth-index calc). For individual assets it is the worst single monthly return, a simpler proxy.

Sheet Correlation
A1: Asset Return Correlation Matrix
A2: Correlation of monthly returns. Green=low/negative (diversifying), Red=high positive (concentrated).
A4: Asset | B4: A01 | C4: A02 | D4: A03 | E4: A04 | F4: A05 | G4: A06 | H4: A07 | I4: A08 | J4: A09 | K4: A10
A5: A01 | B5: =CORREL(Returns!B4:B27,Returns!B4:B27) -> 1 | C5: =CORREL(Returns!B4:B27,Returns!C4:C27) -> 0.059688608 | D5: =CORREL(Returns!B4:B27,Returns!D4:D27) -> 0.099618422 | E5: =CORREL(Returns!B4:B27,Returns!E4:E27) -> -0.14813358 | F5: =CORREL(Returns!B4:B27,Returns!F4:F27) -> 0.084087988 | G5: =CORREL(Returns!B4:B27,Returns!G4:G27) -> -0.10032215 | H5: =CORREL(Returns!B4:B27,Returns!H4:H27) -> 0.015428497 | I5: =CORREL(Returns!B4:B27,Returns!I4:I27) -> 0.012484988 | J5: =CORREL(Returns!B4:B27,Returns!J4:J27) -> -0.015478018 | K5: =CORREL(Returns!B4:B27,Returns!K4:K27) -> -0.30875312
A6: A02 | B6: =CORREL(Returns!C4:C27,Returns!B4:B27) -> 0.059688608 | C6: =CORREL(Returns!C4:C27,Returns!C4:C27) -> 1 | D6: =CORREL(Returns!C4:C27,Returns!D4:D27) -> 0.21980418 | E6: =CORREL(Returns!C4:C27,Returns!E4:E27) -> -0.028967267 | F6: =CORREL(Returns!C4:C27,Returns!F4:F27) -> 0.26289626 | G6: =CORREL(Returns!C4:C27,Returns!G4:G27) -> -0.26847183 | H6: =CORREL(Returns!C4:C27,Returns!H4:H27) -> 0.2040633 | I6: =CORREL(Returns!C4:C27,Returns!I4:I27) -> 0.20634372 | J6: =CORREL(Returns!C4:C27,Returns!J4:J27) -> -0.013865166 | K6: =CORREL(Returns!C4:C27,Returns!K4:K27) -> -0.025677011
A7: A03 | B7: =CORREL(Returns!D4:D27,Returns!B4:B27) -> 0.099618422 | C7: =CORREL(Returns!D4:D27,Returns!C4:C27) -> 0.21980418 | D7: =CORREL(Returns!D4:D27,Returns!D4:D27) -> 1 | E7: =CORREL(Returns!D4:D27,Returns!E4:E27) -> -0.3896892 | F7: =CORREL(Returns!D4:D27,Returns!F4:F27) -> 0.43328609 | G7: =CORREL(Returns!D4:D27,Returns!G4:G27) -> -0.081802649 | H7: =CORREL(Returns!D4:D27,Returns!H4:H27) -> 0.046773905 | I7: =CORREL(Returns!D4:D27,Returns!I4:I27) -> 0.41013777 | J7: =CORREL(Returns!D4:D27,Returns!J4:J27) -> 0.44081217 | K7: =CORREL(Returns!D4:D27,Returns!K4:K27) -> -0.1680292
A8: A04 | B8: =CORREL(Returns!E4:E27,Returns!B4:B27) -> -0.14813358 | C8: =CORREL(Returns!E4:E27,Returns!C4:C27) -> -0.028967267 | D8: =CORREL(Returns!E4:E27,Returns!D4:D27) -> -0.3896892 | E8: =CORREL(Returns!E4:E27,Returns!E4:E27) -> 1 | F8: =CORREL(Returns!E4:E27,Returns!F4:F27) -> 0.15175515 | G8: =CORREL(Returns!E4:E27,Returns!G4:G27) -> -0.3900393 | H8: =CORREL(Returns!E4:E27,Returns!H4:H27) -> -0.092933033 | I8: =CORREL(Returns!E4:E27,Returns!I4:I27) -> -0.13521808 | J8: =CORREL(Returns!E4:E27,Returns!J4:J27) -> 0.22521767 | K8: =CORREL(Returns!E4:E27,Returns!K4:K27) -> 0.25528766
A9: A05 | B9: =CORREL(Returns!F4:F27,Returns!B4:B27) -> 0.084087988 | C9: =CORREL(Returns!F4:F27,Returns!C4:C27) -> 0.26289626 | D9: =CORREL(Returns!F4:F27,Returns!D4:D27) -> 0.43328609 | E9: =CORREL(Returns!F4:F27,Returns!E4:E27) -> 0.15175515 | F9: =CORREL(Returns!F4:F27,Returns!F4:F27) -> 1 | G9: =CORREL(Returns!F4:F27,Returns!G4:G27) -> -0.2983462 | H9: =CORREL(Returns!F4:F27,Returns!H4:H27) -> 0.29188512 | I9: =CORREL(Returns!F4:F27,Returns!I4:I27) -> 0.27533768 | J9: =CORREL(Returns!F4:F27,Returns!J4:J27) -> 0.50666051 | K9: =CORREL(Returns!F4:F27,Returns!K4:K27) -> -0.089650862
A10: A06 | B10: =CORREL(Returns!G4:G27,Returns!B4:B27) -> -0.10032215 | C10: =CORREL(Returns!G4:G27,Returns!C4:C27) -> -0.26847183 | D10: =CORREL(Returns!G4:G27,Returns!D4:D27) -> -0.081802649 | E10: =CORREL(Returns!G4:G27,Returns!E4:E27) -> -0.3900393 | F10: =CORREL(Returns!G4:G27,Returns!F4:F27) -> -0.2983462 | G10: =CORREL(Returns!G4:G27,Returns!G4:G27) -> 1 | H10: =CORREL(Returns!G4:G27,Returns!H4:H27) -> 0.11172451 | I10: =CORREL(Returns!G4:G27,Returns!I4:I27) -> 0.0025324665 | J10: =CORREL(Returns!G4:G27,Returns!J4:J27) -> 0.027214754 | K10: =CORREL(Returns!G4:G27,Returns!K4:K27) -> -0.016295381
A11: A07 | B11: =CORREL(Returns!H4:H27,Returns!B4:B27) -> 0.015428497 | C11: =CORREL(Returns!H4:H27,Returns!C4:C27) -> 0.2040633 | D11: =CORREL(Returns!H4:H27,Returns!D4:D27) -> 0.046773905 | E11: =CORREL(Returns!H4:H27,Returns!E4:E27) -> -0.092933033 | F11: =CORREL(Returns!H4:H27,Returns!F4:F27) -> 0.29188512 | G11: =CORREL(Returns!H4:H27,Returns!G4:G27) -> 0.11172451 | H11: =CORREL(Returns!H4:H27,Returns!H4:H27) -> 1 | I11: =CORREL(Returns!H4:H27,Returns!I4:I27) -> 0.18852895 | J11: =CORREL(Returns!H4:H27,Returns!J4:J27) -> -0.14583429 | K11: =CORREL(Returns!H4:H27,Returns!K4:K27) -> 0.12378494
A12: A08 | B12: =CORREL(Returns!I4:I27,Returns!B4:B27) -> 0.012484988 | C12: =CORREL(Returns!I4:I27,Returns!C4:C27) -> 0.20634372 | D12: =CORREL(Returns!I4:I27,Returns!D4:D27) -> 0.41013777 | E12: =CORREL(Returns!I4:I27,Returns!E4:E27) -> -0.13521808 | F12: =CORREL(Returns!I4:I27,Returns!F4:F27) -> 0.27533768 | G12: =CORREL(Returns!I4:I27,Returns!G4:G27) -> 0.0025324665 | H12: =CORREL(Returns!I4:I27,Returns!H4:H27) -> 0.18852895 | I12: =CORREL(Returns!I4:I27,Returns!I4:I27) -> 1 | J12: =CORREL(Returns!I4:I27,Returns!J4:J27) -> 0.18572365 | K12: =CORREL(Returns!I4:I27,Returns!K4:K27) -> 0.012000646
A13: A09 | B13: =CORREL(Returns!J4:J27,Returns!B4:B27) -> -0.015478018 | C13: =CORREL(Returns!J4:J27,Returns!C4:C27) -> -0.013865166 | D13: =CORREL(Returns!J4:J27,Returns!D4:D27) -> 0.44081217 | E13: =CORREL(Returns!J4:J27,Returns!E4:E27) -> 0.22521767 | F13: =CORREL(Returns!J4:J27,Returns!F4:F27) -> 0.50666051 | G13: =CORREL(Returns!J4:J27,Returns!G4:G27) -> 0.027214754 | H13: =CORREL(Returns!J4:J27,Returns!H4:H27) -> -0.14583429 | I13: =CORREL(Returns!J4:J27,Returns!I4:I27) -> 0.18572365 | J13: =CORREL(Returns!J4:J27,Returns!J4:J27) -> 1 | K13: =CORREL(Returns!J4:J27,Returns!K4:K27) -> -0.062499169
A14: A10 | B14: =CORREL(Returns!K4:K27,Returns!B4:B27) -> -0.30875312 | C14: =CORREL(Returns!K4:K27,Returns!C4:C27) -> -0.025677011 | D14: =CORREL(Returns!K4:K27,Returns!D4:D27) -> -0.1680292 | E14: =CORREL(Returns!K4:K27,Returns!E4:E27) -> 0.25528766 | F14: =CORREL(Returns!K4:K27,Returns!F4:F27) -> -0.089650862 | G14: =CORREL(Returns!K4:K27,Returns!G4:G27) -> -0.016295381 | H14: =CORREL(Returns!K4:K27,Returns!H4:H27) -> 0.12378494 | I14: =CORREL(Returns!K4:K27,Returns!I4:I27) -> 0.012000646 | J14: =CORREL(Returns!K4:K27,Returns!J4:J27) -> -0.062499169 | K14: =CORREL(Returns!K4:K27,Returns!K4:K27) -> 1

Sheet Benchmark
A1: Portfolio vs Benchmark (NIFTY 50)
A3: Date | B3: Portfolio Return % | C3: Benchmark Return % | D3: Excess Return % | E3: Portfolio Cum. Value (Index=100) | F3: Benchmark Cum. Value (Index=100)
A4: =Returns!A4 -> 2024-02-29 | B4: =Returns!L4 -> 0.019379907 | C4: =Returns!M4 -> -0.022700909 | D4: =B4-C4 -> 0.042080816 | E4: =100*(1+B4) -> 101.93799 | F4: =100*(1+C4) -> 97.729909
A5: =Returns!A5 -> 2024-03-31 | B5: =Returns!L5 -> -0.0049533599 | C5: =Returns!M5 -> 0.0044105787 | D5: =B5-C5 -> -0.0093639386 | E5: =E4*(1+B5) -> 101.43306 | F5: =F4*(1+C5) -> 98.160955
A6: =Returns!A6 -> 2024-04-30 | B6: =Returns!L6 -> -0.0078715526 | C6: =Returns!M6 -> 0.02919926 | D6: =B6-C6 -> -0.037070813 | E6: =E5*(1+B6) -> 100.63462 | F6: =F5*(1+C6) -> 101.02718
A7: =Returns!A7 -> 2024-05-31 | B7: =Returns!L7 -> 0.0043553237 | C7: =Returns!M7 -> 0.043630022 | D7: =B7-C7 -> -0.039274698 | E7: =E6*(1+B7) -> 101.07292 | F7: =F6*(1+C7) -> 105.435
A8: =Returns!A8 -> 2024-06-30 | B8: =Returns!L8 -> -0.0050127402 | C8: =Returns!M8 -> -0.039011972 | D8: =B8-C8 -> 0.033999232 | E8: =E7*(1+B8) -> 100.56626 | F8: =F7*(1+C8) -> 101.32177
A9: =Returns!A9 -> 2024-07-31 | B9: =Returns!L9 -> 0.020290343 | C9: =Returns!M9 -> -0.0043798358 | D9: =B9-C9 -> 0.024670179 | E9: =E8*(1+B9) -> 102.60679 | F9: =F8*(1+C9) -> 100.878
A10: =Returns!A10 -> 2024-08-31 | B10: =Returns!L10 -> 0.026882396 | C10: =Returns!M10 -> -0.009997675 | D10: =B10-C10 -> 0.036880071 | E10: =E9*(1+B10) -> 105.3651 | F10: =F9*(1+C10) -> 99.869455
A11: =Returns!A11 -> 2024-09-30 | B11: =Returns!L11 -> 0.016202505 | C11: =Returns!M11 -> -0.017133276 | D11: =B11-C11 -> 0.033335781 | E11: =E10*(1+B11) -> 107.07228 | F11: =F10*(1+C11) -> 98.158364
A12: =Returns!A12 -> 2024-10-31 | B12: =Returns!L12 -> -0.0051998268 | C12: =Returns!M12 -> 0.079618094 | D12: =B12-C12 -> -0.084817921 | E12: =E11*(1+B12) -> 106.51553 | F12: =F11*(1+C12) -> 105.97355
A13: =Returns!A13 -> 2024-11-30 | B13: =Returns!L13 -> 0.020847826 | C13: =Returns!M13 -> 0.025199256 | D13: =B13-C13 -> -0.0043514302 | E13: =E12*(1+B13) -> 108.73614 | F13: =F12*(1+C13) -> 108.644
A14: =Returns!A14 -> 2024-12-31 | B14: =Returns!L14 -> 0.032357377 | C14: =Returns!M14 -> -0.041435163 | D14: =B14-C14 -> 0.07379254 | E14: =E13*(1+B14) -> 112.25456 | F14: =F13*(1+C14) -> 104.14232
A15: =Returns!A15 -> 2025-01-31 | B15: =Returns!L15 -> 0.025217555 | C15: =Returns!M15 -> 0.04571454 | D15: =B15-C15 -> -0.020496985 | E15: =E14*(1+B15) -> 115.08534 | F15: =F14*(1+C15) -> 108.90314
A16: =Returns!A16 -> 2025-02-28 | B16: =Returns!L16 -> 0.011507406 | C16: =Returns!M16 -> 0.093886185 | D16: =B16-C16 -> -0.082378779 | E16: =E15*(1+B16) -> 116.40968 | F16: =F15*(1+C16) -> 119.12764
... A27: =Returns!A27 -> 2026-01-31 | B27: =Returns!L27 -> 0.039196637 | C27: =Returns!M27 -> -0.031975445 | D27: =B27-C27 -> 0.071172082 | E27: =E26*(1+B27) -> 132.27588 | F27: =F26*(1+C27) -> 108.50614
A29: Portfolio Volatility (Ann.) | B29: =Risk_Analysis!D17 -> 0.068454595
A30: Benchmark Volatility (Ann.) | B30: =STDEVP(C4:C27)*SQRT(12) -> 0.16172682
A31: Portfolio Max Drawdown | B31: =Risk_Analysis!I17 -> -0.049302737

Sheet Scenario_Analysis
A1: Scenario / What-If Analysis
A2: Estimated portfolio impact under hypothetical market moves. These are simulations, not predictions.
A4: Scenario | B4: Shock Applied | C4: Assets Affected | D4: Estimated Portfolio Impact % | E4: Estimated ₹ Impact
A5: Scenario 1: Broad Market Rally | B5: +10% | C5: All equity & ETF holdings | D5: =Portfolio_Holdings!K4*0.1+Portfolio_Holdings!K5*0.1+Portfolio_Holdings!K6*0.1+Portfolio_Holdings!K7*0.1+Portfolio_Holdings!K8*0.1+Portfolio_Holdings!K9*0.1+Portfolio_Holdings!K10*0.1+Portfolio_Holdings!K11*0.1+Portfolio_Holdings!K12*0.1+Portfolio_Holdings!K13*0.1 -> 0.1 | E5: =D5*Portfolio_Holdings!$O$1 -> 100000
A6: Scenario 2: Broad Market Correction | B6: -10% | C6: All equity & ETF holdings | D6: =Portfolio_Holdings!K4*-0.1+Portfolio_Holdings!K5*-0.1+Portfolio_Holdings!K6*-0.1+Portfolio_Holdings!K7*-0.1+Portfolio_Holdings!K8*-0.1+Portfolio_Holdings!K9*-0.1+Portfolio_Holdings!K10*-0.1+Portfolio_Holdings!K11*-0.1+Portfolio_Holdings!K12*-0.1+Portfolio_Holdings!K13*-0.1 -> -0.1 | E6: =D6*Portfolio_Holdings!$O$1 -> -100000
A7: Scenario 3: Technology Sector Decline | B7: -20% | C7: TCS, Persistent, Infosys | D7: =Portfolio_Holdings!K5*-0.2+Portfolio_Holdings!K6*-0.2+Portfolio_Holdings!K8*-0.2 -> -0.05690052 | E7: =D7*Portfolio_Holdings!$O$1 -> -56900.52
A8: Scenario 4: Banking Sector Decline | B8: -15% | C8: HDFC Bank | D8: =Portfolio_Holdings!K7*-0.15 -> -0.015487494 | E8: =D8*Portfolio_Holdings!$O$1 -> -15487.494
A9: Scenario 5: Flight to Gold (Gold Up, Equities Down) | B9: Gold +8%, Equities -5% | C9: Gold ETF +8%, equities -5% (excl. debt) | D9: =Portfolio_Holdings!K4*-0.05+Portfolio_Holdings!K5*-0.05+Portfolio_Holdings!K6*-0.05+Portfolio_Holdings!K7*-0.05+Portfolio_Holdings!K8*-0.05+Portfolio_Holdings!K9*-0.05+Portfolio_Holdings!K10*-0.05+Portfolio_Holdings!K11*-0.05+Portfolio_Holdings!K12*0.08+Portfolio_Holdings!K13*0 -> -0.029970913 | E9: =D9*Portfolio_Holdings!$O$1 -> -29970.913

Sheet Rebalancing
A1: Portfolio Rebalancing Recommendation
A3: Asset ID | B3: Asset Name | C3: Current Weight % | D3: Target Weight % | E3: Difference % | F3: Action | G3: ₹ Amount to Buy/Sell
A4: A01 | B4: =Portfolio_Holdings!B4 -> Reliance Industries | C4: =Portfolio_Holdings!K4 -> 0.10073913 | D4: 0.1 | E4: =D4-C4 -> -0.00073913003 | F4: =IF(E4>0.005,"BUY",IF(E4<-0.005,"SELL","HOLD")) -> HOLD | G4: =E4*Portfolio_Holdings!$O$1 -> -739.13003
A5: A02 | B5: =Portfolio_Holdings!B5 -> TCS | C5: =Portfolio_Holdings!K5 -> 0.071650801 | D5: 0.09 | E5: =D5-C5 -> 0.018349199 | F5: =IF(E5>0.005,"BUY",IF(E5<-0.005,"SELL","HOLD")) -> BUY | G5: =E5*Portfolio_Holdings!$O$1 -> 18349.199
A6: A03 | B6: =Portfolio_Holdings!B6 -> Persistent Systems | C6: =Portfolio_Holdings!K6 -> 0.11123131 | D6: 0.08 | E6: =D6-C6 -> -0.031231311 | F6: =IF(E6>0.005,"BUY",IF(E6<-0.005,"SELL","HOLD")) -> SELL | G6: =E6*Portfolio_Holdings!$O$1 -> -31231.311
A7: A04 | B7: =Portfolio_Holdings!B7 -> HDFC Bank | C7: =Portfolio_Holdings!K7 -> 0.10324996 | D7: 0.11 | E7: =D7-C7 -> 0.0067500367 | F7: =IF(E7>0.005,"BUY",IF(E7<-0.005,"SELL","HOLD")) -> BUY | G7: =E7*Portfolio_Holdings!$O$1 -> 6750.0367
A8: A05 | B8: =Portfolio_Holdings!B8 -> Infosys | C8: =Portfolio_Holdings!K8 -> 0.10162049 | D8: 0.1 | E8: =D8-C8 -> -0.0016204884 | F8: =IF(E8>0.005,"BUY",IF(E8<-0.005,"SELL","HOLD")) -> HOLD | G8: =E8*Portfolio_Holdings!$O$1 -> -1620.4884
A9: A06 | B9: =Portfolio_Holdings!B9 -> ITC Ltd | C9: =Portfolio_Holdings!K9 -> 0.068855245 | D9: 0.09 | E9: =D9-C9 -> 0.021144755 | F9: =IF(E9>0.005,"BUY",IF(E9<-0.005,"SELL","HOLD")) -> BUY | G9: =E9*Portfolio_Holdings!$O$1 -> 21144.755
A10: A07 | B10: =Portfolio_Holdings!B10 -> Sun Pharma | C10: =Portfolio_Holdings!K10 -> 0.11164966 | D10: 0.09 | E10: =D10-C10 -> -0.021649655 | F10: =IF(E10>0.005,"BUY",IF(E10<-0.005,"SELL","HOLD")) -> SELL | G10: =E10*Portfolio_Holdings!$O$1 -> -21649.655
A11: A08 | B11: =Portfolio_Holdings!B11 -> Nifty50 Index ETF | C11: =Portfolio_Holdings!K11 -> 0.12196561 | D11: 0.13 | E11: =D11-C11 -> 0.0080343944 | F11: =IF(E11>0.005,"BUY",IF(E11<-0.005,"SELL","HOLD")) -> BUY | G11: =E11*Portfolio_Holdings!$O$1 -> 8034.3944
A12: A09 | B12: =Portfolio_Holdings!B12 -> Gold ETF | C12: =Portfolio_Holdings!K12 -> 0.11971496 | D12: 0.11 | E12: =D12-C12 -> -0.009714959 | F12: =IF(E12>0.005,"BUY",IF(E12<-0.005,"SELL","HOLD")) -> SELL | G12: =E12*Portfolio_Holdings!$O$1 -> -9714.959
A13: A10 | B13: =Portfolio_Holdings!B13 -> Liquid/Debt Fund | C13: =Portfolio_Holdings!K13 -> 0.089322842 | D13: 0.1 | E13: =D13-C13 -> 0.010677158 | F13: =IF(E13>0.005,"BUY",IF(E13<-0.005,"SELL","HOLD")) -> BUY | G13: =E13*Portfolio_Holdings!$O$1 -> 10677.158
B14: TOTAL | D14: =SUM(D4:D13) -> 1

Sheet KPI_Summary
A1: Portfolio KPI Summary
A4: Total Investment (₹) | B4: =Portfolio_Holdings!O1 -> 1000000
A5: Current Portfolio Value (₹) | B5: =Portfolio_Holdings!J14 -> 1265073.9
A6: Total Gain/Loss (₹) | B6: =B5-B4 -> 265073.95
A7: Total Return % | B7: =B5/B4-1 -> 0.26507395
A8: Annualized Return % | B8: =Risk_Analysis!F17 -> 0.14298762
A9: Portfolio Volatility (Ann.) % | B9: =Risk_Analysis!D17 -> 0.068454595
A10: Beta vs Benchmark | B10: =Risk_Analysis!E17 -> -0.070977831
A11: Sharpe Ratio | B11: =Risk_Analysis!G17 -> 1.0662194
A12: Maximum Drawdown % | B12: =Risk_Analysis!I17 -> -0.049302737
A13: 1-Month 95% VaR (₹) | B13: =Risk_Analysis!J17 -> 41123.853
A14: Benchmark Annualized Return % | B14: =Returns!M30 -> 0.054088614
A15: Excess Return vs Benchmark % | B15: =B8-B14 -> 0.088899003
A16: Equity Allocation % (excl. Gold/Debt) | B16: =1-Portfolio_Holdings!K12-Portfolio_Holdings!K13 -> 0.7909622
A17: Largest Single-Asset Concentration % | B17: =MAX(Portfolio_Holdings!K4:K13) -> 0.12196561

Sheet Dashboard
A1: Stock Market Portfolio Risk & Return Dashboard
A2: Simulated educational data | Investor: Mr. Arjun Mehta | Benchmark: NIFTY 50
A4: Portfolio Value (₹) | C4: Total Return % | E4: Annualized Return % | G4: Volatility (Ann.) % | I4: Sharpe Ratio | K4: Max Drawdown %
A5: =KPI_Summary!B5 -> 1265073.9 | C5: =KPI_Summary!B7 -> 0.26507395 | E5: =KPI_Summary!B8 -> 0.14298762 | G5: =KPI_Summary!B9 -> 0.068454595 | I5: =KPI_Summary!B11 -> 1.0662194 | K5: =KPI_Summary!B12 -> -0.049302737
